privacy/qa/commons/mac/__init__.py
privacy.qa.commons.mac-0.0.1.dist-info/METADATA
privacy.qa.commons.mac-0.0.1.dist-info/WHEEL
privacy.qa.commons.mac-0.0.1.dist-info/top_level.txt
privacy.qa.commons.mac-0.0.1.dist-info/RECORD
