Metadata-Version: 2.1
Name: privacy.qa.commons.mac
Version: 0.0.1
Summary: Testing library
Home-page: UNKNOWN
Author: Teal team
License: UNKNOWN
Platform: UNKNOWN
Classifier: Programming Language :: Python :: 3
